[
  {"supercat_id": 1, "name": "person",     "cat_id": 1},
  {"supercat_id": 2, "name": "bicycle",    "cat_id": 2},
  {"supercat_id": 2, "name": "car",        "cat_id": 3},
  {"supercat_id": 2, "name": "motorcycle", "cat_id": 4},
  {"supercat_id": 2, "name": "airplane",   "cat_id": 5},
  {"supercat_id": 2, "name": "bus",        "cat_id": 6},
  {"supercat_id": 2, "name": "train",      "cat_id": 7},
  {"supercat_id": 2, "name": "truck",      "cat_id": 8},
  {"supercat_id": 2, "name": "boat",          "cat_id": 9},
  {"supercat_id": 3, "name": "traffic light", "cat_id": 10},
  {"supercat_id": 3, "name": "fire hydrant",  "cat_id": 11},
  {"supercat_id": 3, "name": "stop sign",     "cat_id": 13},
  {"supercat_id": 3, "name": "parking meter", "cat_id": 14},
  {"supercat_id": 3, "name": "bench",  "cat_id": 15},
  {"supercat_id": 4, "name": "bird",   "cat_id": 16},
  {"supercat_id": 4, "name": "cat",    "cat_id": 17},
  {"supercat_id": 4, "name": "dog",    "cat_id": 18},
  {"supercat_id": 4, "name": "horse",  "cat_id": 19},
  {"supercat_id": 4, "name": "sheep",  "cat_id": 20},
  {"supercat_id": 4, "name": "cow",      "cat_id": 21},
  {"supercat_id": 4, "name": "elephant", "cat_id": 22},
  {"supercat_id": 4, "name": "bear",     "cat_id": 23},
  {"supercat_id": 4, "name": "zebra",    "cat_id": 24},
  {"supercat_id": 4, "name": "giraffe",  "cat_id": 25},
  {"supercat_id": 1, "name": "backpack", "cat_id": 27},
  {"supercat_id": 1, "name": "umbrella", "cat_id": 28},
  {"supercat_id": 1, "name": "handbag",  "cat_id": 31},
  {"supercat_id": 1, "name": "tie",      "cat_id": 32},
  {"supercat_id": 1, "name": "suitcase", "cat_id": 33},
  {"supercat_id": 6, "name": "frisbee", "cat_id": 34},
  {"supercat_id": 6, "name": "skis", "cat_id": 35},
  {"supercat_id": 6, "name": "snowboard", "cat_id": 36},
  {"supercat_id": 6, "name": "sports ball", "cat_id": 37},
  {"supercat_id": 6, "name": "kite", "cat_id": 38},
  {"supercat_id": 6, "name": "baseball bat", "cat_id": 39},
  {"supercat_id": 6, "name": "baseball glove", "cat_id": 40},
  {"supercat_id": 6, "name": "skateboard", "cat_id": 41},
  {"supercat_id": 6, "name": "surfboard", "cat_id": 42},
  {"supercat_id": 6, "name": "tennis racket", "cat_id": 43},
  {"supercat_id": 7, "name": "bottle", "cat_id": 44},
  {"supercat_id": 7, "name": "wine glass", "cat_id": 46},
  {"supercat_id": 7, "name": "cup", "cat_id": 47},
  {"supercat_id": 7, "name": "fork", "cat_id": 48},
  {"supercat_id": 7, "name": "knife", "cat_id": 49},
  {"supercat_id": 7, "name": "spoon", "cat_id": 50},
  {"supercat_id": 7, "name": "bowl", "cat_id": 51},
  {"supercat_id": 8, "name": "banana", "cat_id": 52},
  {"supercat_id": 8, "name": "apple", "cat_id": 53},
  {"supercat_id": 8, "name": "sandwich", "cat_id": 54},
  {"supercat_id": 8, "name": "orange", "cat_id": 55},
  {"supercat_id": 8, "name": "broccoli", "cat_id": 56},
  {"supercat_id": 8, "name": "carrot", "cat_id": 57},
  {"supercat_id": 8, "name": "hot dog", "cat_id": 58},
  {"supercat_id": 8, "name": "pizza", "cat_id": 59},
  {"supercat_id": 8, "name": "donut", "cat_id": 60},
  {"supercat_id": 8, "name": "cake", "cat_id": 61},
  {"supercat_id": 9, "name": "chair", "cat_id": 62},
  {"supercat_id": 9, "name": "couch", "cat_id": 63},
  {"supercat_id": 9, "name": "potted plant", "cat_id": 64},
  {"supercat_id": 9, "name": "bed", "cat_id": 65},
  {"supercat_id": 9, "name": "dining table", "cat_id": 67},
  {"supercat_id": 9, "name": "toilet", "cat_id": 70},
  {"supercat_id": 10, "name": "tv", "cat_id": 72},
  {"supercat_id": 10, "name": "laptop", "cat_id": 73},
  {"supercat_id": 10, "name": "mouse", "cat_id": 74},
  {"supercat_id": 10, "name": "remote", "cat_id": 75},
  {"supercat_id": 10, "name": "keyboard", "cat_id": 76},
  {"supercat_id": 10, "name": "cell phone", "cat_id": 77},
  {"supercat_id": 11, "name": "microwave", "cat_id": 78},
  {"supercat_id": 11, "name": "oven", "cat_id": 79},
  {"supercat_id": 11, "name": "toaster", "cat_id": 80},
  {"supercat_id": 11, "name": "sink", "cat_id": 81},
  {"supercat_id": 11, "name": "refrigerator", "cat_id": 82},
  {"supercat_id": 12, "name": "book",         "cat_id": 84},
  {"supercat_id": 12, "name": "clock",      "cat_id": 85},
  {"supercat_id": 12, "name": "vase",       "cat_id": 86},
  {"supercat_id": 12, "name": "scissors",   "cat_id": 87},
  {"supercat_id": 12, "name": "teddy bear", "cat_id": 88},
  {"supercat_id": 12, "name": "hair drier", "cat_id": 89},
  {"supercat_id": 12, "name": "toothbrush", "cat_id": 90}
]
